MANIFEST.in
README.rst
setup.cfg
setup.py
onlinelinguisticdatabase/__init__.py
onlinelinguisticdatabase/websetup.py
onlinelinguisticdatabase.egg-info/PKG-INFO
onlinelinguisticdatabase.egg-info/SOURCES.txt
onlinelinguisticdatabase.egg-info/dependency_links.txt
onlinelinguisticdatabase.egg-info/entry_points.txt
onlinelinguisticdatabase.egg-info/not-zip-safe
onlinelinguisticdatabase.egg-info/paster_plugins.txt
onlinelinguisticdatabase.egg-info/requires.txt
onlinelinguisticdatabase.egg-info/top_level.txt
onlinelinguisticdatabase/config/__init__.py
onlinelinguisticdatabase/config/deployment.ini_tmpl
onlinelinguisticdatabase/config/environment.py
onlinelinguisticdatabase/config/middleware.py
onlinelinguisticdatabase/config/routing.py
onlinelinguisticdatabase/controllers/__init__.py
onlinelinguisticdatabase/controllers/applicationsettings.py
onlinelinguisticdatabase/controllers/collectionbackups.py
onlinelinguisticdatabase/controllers/corpora.py
onlinelinguisticdatabase/controllers/corpusbackups.py
onlinelinguisticdatabase/controllers/cors.py
onlinelinguisticdatabase/controllers/elicitationmethods.py
onlinelinguisticdatabase/controllers/error.py
onlinelinguisticdatabase/controllers/files.py
onlinelinguisticdatabase/controllers/formbackups.py
onlinelinguisticdatabase/controllers/forms.py
onlinelinguisticdatabase/controllers/formsearches.py
onlinelinguisticdatabase/controllers/info.py
onlinelinguisticdatabase/controllers/keyboards.py
onlinelinguisticdatabase/controllers/languages.py
onlinelinguisticdatabase/controllers/login.py
onlinelinguisticdatabase/controllers/morphemelanguagemodelbackups.py
onlinelinguisticdatabase/controllers/morphemelanguagemodels.py
onlinelinguisticdatabase/controllers/morphologicalparserbackups.py
onlinelinguisticdatabase/controllers/morphologicalparsers.py
onlinelinguisticdatabase/controllers/morphologies.py
onlinelinguisticdatabase/controllers/morphologybackups.py
onlinelinguisticdatabase/controllers/oldcollections.py
onlinelinguisticdatabase/controllers/orthographies.py
onlinelinguisticdatabase/controllers/pages.py
onlinelinguisticdatabase/controllers/phonologies.py
onlinelinguisticdatabase/controllers/phonologybackups.py
onlinelinguisticdatabase/controllers/rememberedforms.py
onlinelinguisticdatabase/controllers/sources.py
onlinelinguisticdatabase/controllers/speakers.py
