Metadata-Version: 1.1
Name: onlinelinguisticdatabase
Version: 2.0.0
Summary: A program for building web services that facilitate collaborative
Home-page: http://www.onlinelinguisticdatabase.org
Author: Joel Dunham
Author-email: jrwdunham@gmail.com
License: Apache v. 2.0
Platform: UNKNOWN
Classifier: Development Status :: 3 - Alpha
Classifier: Framework :: Pylons
Classifier: Intended Audience :: Developers
Classifier: Intended Audience :: Education
Classifier: Intended Audience :: Science/Research
Classifier: License :: OSI Approved :: Apache Software License
Classifier: Natural Language :: English
Classifier: Programming Language :: Python
Classifier: Topic :: Database :: Front-Ends
Classifier: Topic :: Education
